song_scrounger/__init__.py
song_scrounger/document_parser.py
song_scrounger/song_scrounger.py
song_scrounger/spotify_client.py
song_scrounger/util.py
song_scrounger/models/__init__.py
song_scrounger/models/album.py
song_scrounger/models/song.py
tests/__init__.py
tests/helper.py
tests/test_document_parser.py
tests/test_song_scrounger.py
tests/test_spotify_client.py
tests/test_util.py
songscrounger-0.2.3.dist-info/LICENSE
songscrounger-0.2.3.dist-info/METADATA
songscrounger-0.2.3.dist-info/WHEEL
songscrounger-0.2.3.dist-info/top_level.txt
songscrounger-0.2.3.dist-info/RECORD
