Metadata-Version: 2.1
Name: songscrounger
Version: 0.2.3
Summary: A tool for finding Spotify tracks and albums from names mentioned in text.
Home-page: https://github.com/okjuan/song-scrounger
Author: Juan Carlos Gallegos Dupuis
Author-email: jcgallegdup@gmail.com
License: UNKNOWN
Platform: UNKNOWN
Classifier: Programming Language :: Python :: 3
Classifier: License :: OSI Approved :: MIT License
Classifier: Operating System :: OS Independent
Requires-Python: >=3.8
Requires-Dist: spotify (>=0.10.2)
